{"cameraMode":{"drawMode":0,"name":"Shaded","section":"Shading Mode"},"sceneLighting":true,"audioPlay":false,"sceneViewState":{"m_AlwaysRefresh":false,"showFog":true,"showSkybox":true,"showFlares":true,"showImageEffects":true,"showParticleSystems":true,"showVisualEffectGraphs":true,"m_FxEnabled":true},"in2DMode":false,"pivot":{"x":-31.699567794799806,"y":-5.3505706787109379,"z":-11.89026165008545},"rotation":{"x":-0.26680752635002139,"y":0.6990704536437988,"z":-0.32128241658210757,"w":-0.580493152141571},"size":27.766611099243165,"orthographic":false}